CHANGELOG.rst
LICENSE
MANIFEST.in
README-PYPI.rst
README.rst
setup.py
bethesda_structs/__init__.py
bethesda_structs/__version__.py
bethesda_structs/_common.py
bethesda_structs/exceptions.py
bethesda_structs.egg-info/PKG-INFO
bethesda_structs.egg-info/SOURCES.txt
bethesda_structs.egg-info/dependency_links.txt
bethesda_structs.egg-info/requires.txt
bethesda_structs.egg-info/top_level.txt
bethesda_structs/archive/__init__.py
bethesda_structs/archive/_common.py
bethesda_structs/archive/bsa.py
bethesda_structs/archive/btdx.py
bethesda_structs/contrib/__init__.py
bethesda_structs/contrib/dds.py
bethesda_structs/plugin/__init__.py
bethesda_structs/plugin/_common.py
bethesda_structs/plugin/fo3.py
bethesda_structs/plugin/fnv/__init__.py
bethesda_structs/plugin/fnv/_common.py
bethesda_structs/plugin/fnv/records.py