Metadata-Version: 2.1
Name: bethesda-structs
Version: 0.1.4
Summary: A parser for Bethesda's file formats
Home-page: https://github.com/stephen-bunn/bethesda-structs
Author: Stephen Bunn
Author-email: stephen@bunn.io
License: MIT License
Keywords: bethesda,filetype,structures,archive,python36,construct
Platform: UNKNOWN
Classifier: Development Status :: 2 - Pre-Alpha
Classifier: Programming Language :: Python :: 3.6
Classifier: License :: OSI Approved :: GNU General Public License v3 (GPLv3)
Classifier: Intended Audience :: Developers
Classifier: Operating System :: POSIX
Classifier: Operating System :: MacOS :: MacOS X
Classifier: Operating System :: Microsoft :: Windows
Classifier: Natural Language :: English
Classifier: Topic :: Software Development :: Build Tools
Classifier: Topic :: Software Development :: Disassemblers
Classifier: Topic :: Software Development :: Pre-processors
Classifier: Topic :: Utilities
Requires-Python: >=3.6
Provides-Extra: dev
